autofix_bot/__init__.py
autofix_bot/_base_client.py
autofix_bot/_client.py
autofix_bot/_compat.py
autofix_bot/_constants.py
autofix_bot/_exceptions.py
autofix_bot/_files.py
autofix_bot/_models.py
autofix_bot/_qs.py
autofix_bot/_resource.py
autofix_bot/_response.py
autofix_bot/_streaming.py
autofix_bot/_types.py
autofix_bot/_version.py
autofix_bot/py.typed
autofix_bot/_utils/__init__.py
autofix_bot/_utils/_compat.py
autofix_bot/_utils/_datetime_parse.py
autofix_bot/_utils/_logs.py
autofix_bot/_utils/_proxy.py
autofix_bot/_utils/_reflection.py
autofix_bot/_utils/_resources_proxy.py
autofix_bot/_utils/_streams.py
autofix_bot/_utils/_sync.py
autofix_bot/_utils/_transform.py
autofix_bot/_utils/_typing.py
autofix_bot/_utils/_utils.py
autofix_bot/lib/.keep
autofix_bot/resources/__init__.py
autofix_bot/resources/analysis.py
autofix_bot/resources/workspace.py
autofix_bot/resources/repositories/__init__.py
autofix_bot/resources/repositories/repositories.py
autofix_bot/resources/repositories/syncs.py
autofix_bot/types/__init__.py
autofix_bot/types/analysis.py
autofix_bot/types/analysis_create_params.py
autofix_bot/types/analysis_list_fixes_params.py
autofix_bot/types/analysis_list_fixes_response.py
autofix_bot/types/analysis_list_issues_params.py
autofix_bot/types/analysis_list_issues_response.py
autofix_bot/types/analysis_list_params.py
autofix_bot/types/analysis_list_response.py
autofix_bot/types/fix.py
autofix_bot/types/issue.py
autofix_bot/types/language.py
autofix_bot/types/paginated_list.py
autofix_bot/types/repository.py
autofix_bot/types/repository_create_params.py
autofix_bot/types/repository_list_params.py
autofix_bot/types/repository_list_response.py
autofix_bot/types/repository_update_params.py
autofix_bot/types/workspace_retrieve_response.py
autofix_bot/types/repositories/__init__.py
autofix_bot/types/repositories/sync.py
autofix_bot/types/repositories/sync_create_params.py
autofix_bot/types/repositories/sync_list_params.py
autofixbot-0.1.0.dist-info/METADATA
autofixbot-0.1.0.dist-info/WHEEL
autofixbot-0.1.0.dist-info/licenses/LICENSE
autofixbot-0.1.0.dist-info/RECORD
